ninka/__init__.py
ninka/indieauth.py
ninka/micropub.py
ninka-0.3.4.dist-info/DESCRIPTION.rst
ninka-0.3.4.dist-info/METADATA
ninka-0.3.4.dist-info/RECORD
ninka-0.3.4.dist-info/WHEEL
ninka-0.3.4.dist-info/metadata.json
ninka-0.3.4.dist-info/pbr.json
ninka-0.3.4.dist-info/top_level.txt
