Metadata-Version: 2.0
Name: ninka
Version: 0.3.4
Summary: Indieauth Toolkit
Home-page: https://github.com/bear/ninka
Author: bear (Mike Taylor)
Author-email: bear@bear.im
License: MIT
Download-URL: https://pypi.python.org/pypi/ninka
Platform: Any
Classifier: Development Status :: 4 - Beta
Classifier: Intended Audience :: Developers
Classifier: License :: OSI Approved :: MIT License
Classifier: Topic :: Software Development :: Libraries :: Python Modules
Requires-Dist: beautifulsoup4
Requires-Dist: lxml
Requires-Dist: requests
Requires-Dist: ronkyuu
